[
  {
    "street_address": "123 Kurfürstendamm",
    "street_name": "Kurfürstendamm",
    "building_number": "123",
    "city": "Berlin",
    "state": "Berlin",
    "postal_code": "10709",
    "country": "Germany",
    "country_code": "DE",
    "currency": "EUR"
  },
  {
    "street_address": "456 Marienplatz",
    "street_name": "Marienplatz",
    "building_number": "456",
    "city": "Munich",
    "state": "Bavaria",
    "postal_code": "80331",
    "country": "Germany",
    "country_code": "DE",
    "currency": "EUR"
  },
  {
    "street_address": "789 Königstraße",
    "street_name": "Königstraße",
    "building_number": "789",
    "city": "Stuttgart",
    "state": "Baden-Württemberg",
    "postal_code": "70173",
    "country": "Germany",
    "country_code": "DE",
    "currency": "EUR"
  },
  {
    "street_address": "101 Zeil",
    "street_name": "Zeil",
    "building_number": "101",
    "city": "Frankfurt",
    "state": "Hesse",
    "postal_code": "60313",
    "country": "Germany",
    "country_code": "DE",
    "currency": "EUR"
  },
  {
    "street_address": "34 Schildergasse",
    "street_name": "Schildergasse",
    "building_number": "34",
    "city": "Cologne",
    "state": "North Rhine-Westphalia",
    "postal_code": "50667",
    "country": "Germany",
    "country_code": "DE",
    "currency": "EUR"
  }
]
