[
  {
    "name": "Grace Nakimera",
    "gender": "Female",
    "phone_number": "+256 772 123456",
    "street_address": "123 Kampala Road",
    "street_name": "Kampala Road",
    "building_number": "123",
    "city": "Kampala",
    "state": "Central Region",
    "postal_code": "256",
    "country": "Uganda",
    "country_code": "UG",
    "currency": "UGX"
  },
  {
    "name": "Peter Okello",
    "gender": "Male",
    "phone_number": "+256 701 234567",
    "street_address": "45 Gulu Main Street",
    "street_name": "Gulu Main Street",
    "building_number": "45",
    "city": "Gulu",
    "state": "Northern Region",
    "postal_code": "256",
    "country": "Uganda",
    "country_code": "UG",
    "currency": "UGX"
  },
  {
    "name": "Joan Kabonesa",
    "gender": "Female",
    "phone_number": "+256 782 345678",
    "street_address": "78 Kabale Street",
    "street_name": "Kabale Street",
    "building_number": "78",
    "city": "Kabale",
    "state": "Western Region",
    "postal_code": "256",
    "country": "Uganda",
    "country_code": "UG",
    "currency": "UGX"
  },
  {
    "name": "David Musoke",
    "gender": "Male",
    "phone_number": "+256 752 456789",
    "street_address": "101 Jinja Road",
    "street_name": "Jinja Road",
    "building_number": "101",
    "city": "Jinja",
    "state": "Eastern Region",
    "postal_code": "256",
    "country": "Uganda",
    "country_code": "UG",
    "currency": "UGX"
  },
  {
    "name": "Sarah Namutebi",
    "gender": "Female",
    "phone_number": "+256 783 567890",
    "street_address": "34 Entebbe Street",
    "street_name": "Entebbe Street",
    "building_number": "34",
    "city": "Entebbe",
    "state": "Central Region",
    "postal_code": "256",
    "country": "Uganda",
    "country_code": "UG",
    "currency": "UGX"
  },
  {
    "name": "Ronald Ssekandi",
    "gender": "Male",
    "phone_number": "+256 704 678901",
    "street_address": "66 Makerere Hill Road",
    "street_name": "Makerere Hill Road",
    "building_number": "66",
    "city": "Kampala",
    "state": "Central Region",
    "postal_code": "256",
    "country": "Uganda",
    "country_code": "UG",
    "currency": "UGX"
  },
  {
    "name": "Agnes Alobo",
    "gender": "Female",
    "phone_number": "+256 764 789012",
    "street_address": "88 Lira Road",
    "street_name": "Lira Road",
    "building_number": "88",
    "city": "Lira",
    "state": "Northern Region",
    "postal_code": "256",
    "country": "Uganda",
    "country_code": "UG",
    "currency": "UGX"
  },
  {
    "name": "Sam Kintu",
    "gender": "Male",
    "phone_number": "+256 776 890123",
    "street_address": "55 Fort Portal Road",
    "street_name": "Fort Portal Road",
    "building_number": "55",
    "city": "Fort Portal",
    "state": "Western Region",
    "postal_code": "256",
    "country": "Uganda",
    "country_code": "UG",
    "currency": "UGX"
  },
  {
    "name": "Beatrice Akello",
    "gender": "Female",
    "phone_number": "+256 705 901234",
    "street_address": "23 Mbale Avenue",
    "street_name": "Mbale Avenue",
    "building_number": "23",
    "city": "Mbale",
    "state": "Eastern Region",
    "postal_code": "256",
    "country": "Uganda",
    "country_code": "UG",
    "currency": "UGX"
  },
  {
    "name": "Robert Muwonge",
    "gender": "Male",
    "phone_number": "+256 785 012345",
    "street_address": "70 Masaka Road",
    "street_name": "Masaka Road",
    "building_number": "70",
    "city": "Masaka",
    "state": "Central Region",
    "postal_code": "256",
    "country": "Uganda",
    "country_code": "UG",
    "currency": "UGX"
  }
]
